irpf_investidor/__init__.py
irpf_investidor/__main__.py
irpf_investidor/b3.py
irpf_investidor/formatting.py
irpf_investidor/prompt.py
irpf_investidor/py.typed
irpf_investidor/report_reader.py
irpf_investidor/responses.py
irpf_investidor-2025.16.5.dist-info/METADATA
irpf_investidor-2025.16.5.dist-info/WHEEL
irpf_investidor-2025.16.5.dist-info/entry_points.txt
irpf_investidor-2025.16.5.dist-info/licenses/LICENSE
irpf_investidor-2025.16.5.dist-info/RECORD
