Metadata-Version: 2.4
Name: irpf-investidor
Version: 2025.16.5
Summary: IRPF Investidor
Project-URL: Changelog, https://github.com/staticdev/irpf-investidor/releases
Author-email: staticdev <staticdev-support@proton.me>
License-Expression: MIT
License-File: LICENSE
Classifier: Development Status :: 5 - Production/Stable
Requires-Python: >=3.11
Requires-Dist: click>=8.1.7
Requires-Dist: pandas>=2.2.3
Requires-Dist: prompt-toolkit>=3.0.43
Requires-Dist: xlrd>=2.0.1
